{
    "users": {
        "#j3a1": {},
        "#o123": {},
        "#k312": {}
    },
    "attractions": [
     
        {
            "id": 12,
            "name": "Skałki twardowskiego",
            "desc": "Et sit laboris aliquip tempor pariatur culpa nulla laboris Lorem in consequat nulla. Sit aliqua cillum et tempor velit dolore minim aute proident. Laboris ut incididunt eiusmod ea. Cillum labore exercitation nostrud labore eu minim id ut commodo reprehenderit enim.",
            "long": "50.0",
            "lat": "19.0",
            "image": "https://media.discordapp.net/attachments/774371755531173888/974948678114611260/zakrzowek.jpg",
            "popularity": 3,
            "score": 8
        },

        {
            "id": 12,
            "name": "Lebanon quarry",
            "desc": "Et sit laboris aliquip tempor pariatur culpa nulla laboris Lorem in consequat nulla. Sit aliqua cillum et tempor velit dolore minim aute proident. Laboris ut incididunt eiusmod ea. Cillum labore exercitation nostrud labore eu minim id ut commodo reprehenderit enim.",
            "long": "50.0",
            "lat": "19.0",
            "image": "https://media.discordapp.net/attachments/774371755531173888/974948945824464926/liban.jpg",
            "popularity": 3,
            "score": 7
        },


        {
            "id": 13,
            "name": "Krakow Technology Park",
            "desc": "Et sit laboris aliquip tempor pariatur culpa nulla laboris Lorem in consequat nulla. Sit aliqua cillum et tempor velit dolore minim aute proident. Laboris ut incididunt eiusmod ea. Cillum labore exercitation nostrud labore eu minim id ut commodo reprehenderit enim.",
            "long": "50.0",
            "lat": "19.0",
            "image": "https://media.discordapp.net/attachments/774371755531173888/974949476043227186/280028702_2133111713531382_8052369464993999624_n.jpg?width=1175&height=660",
            "popularity": 3,
            "score": 10
        },

        {
            "id": 14,
            "name": "Fort 53a - Winnica",
            "desc": "Et sit laboris aliquip tempor pariatur culpa nulla laboris Lorem in consequat nulla. Sit aliqua cillum et tempor velit dolore minim aute proident. Laboris ut incididunt eiusmod ea. Cillum labore exercitation nostrud labore eu minim id ut commodo reprehenderit enim.",
            "long": "50.0",
            "lat": "19.0",
            "image": "https://media.discordapp.net/attachments/774371755531173888/974949762036035644/winnica.jpg",
            "popularity": 3,
            "score": 7
        },

        {
            "id": 15,
            "name": "Borkowski Wood",
            "desc": "Et sit laboris aliquip tempor pariatur culpa nulla laboris Lorem in consequat nulla. Sit aliqua cillum et tempor velit dolore minim aute proident. Laboris ut incididunt eiusmod ea. Cillum labore exercitation nostrud labore eu minim id ut commodo reprehenderit enim.",
            "long": "50.0",
            "lat": "19.0",
            "image": "https://media.discordapp.net/attachments/774371755531173888/974950209719246888/unknown.png",
            "popularity": 3,
            "score": 9
        },

        {
            "id": 16,
            "name": "Restaurant 'Kto Wpuścił Skowronka'",
            "desc": "Et sit laboris aliquip tempor pariatur culpa nulla laboris Lorem in consequat nulla. Sit aliqua cillum et tempor velit dolore minim aute proident. Laboris ut incididunt eiusmod ea. Cillum labore exercitation nostrud labore eu minim id ut commodo reprehenderit enim.",
            "long": "50.0",
            "lat": "19.0",
            "image": "https://media.discordapp.net/attachments/774371755531173888/974948945824464926/liban.jpg",
            "popularity": 3,
            "score": 5
        }

    ]
}